[
  {
    "py/object": "model.group.Group",
    "name": "",
    "header": "",
    "footer": "",
    "id": null
  },
  {
    "py/object": "model.group.Group",
    "name": "nametueZq7yCr",
    "header": "headuxGDJG2e",
    "footer": "footC4Okoaua",
    "id": null
  },
  {
    "py/object": "model.group.Group",
    "name": "nameY5u",
    "header": "headbjWW8JSEIQLBtrX1D",
    "footer": "foots2D0U5l1CQYOhxBN3kG",
    "id": null
  },
  {
    "py/object": "model.group.Group",
    "name": "namecTEQ",
    "header": "headfqj7P",
    "footer": "footUp64BS6g",
    "id": null
  },
  {
    "py/object": "model.group.Group",
    "name": "namei",
    "header": "headdmrOey65qB",
    "footer": "footd",
    "id": null
  },
  {
    "py/object": "model.group.Group",
    "name": "nameYLvc",
    "header": "headAXVWRal7Jc0A",
    "footer": "foot3Stc57UFDB4IqHhRiE",
    "id": null
  }
]